mousechd_napari/__init__.py
mousechd_napari/_reader.py
mousechd_napari/_utils.py
mousechd_napari/_widget.py
mousechd_napari/napari.yaml
mousechd_napari/sample_data.py
mousechd_napari/assets/__init__.py
mousechd_napari-0.0.4.dist-info/LICENSE
mousechd_napari-0.0.4.dist-info/METADATA
mousechd_napari-0.0.4.dist-info/WHEEL
mousechd_napari-0.0.4.dist-info/entry_points.txt
mousechd_napari-0.0.4.dist-info/top_level.txt
mousechd_napari-0.0.4.dist-info/RECORD
